examples/mnistwild/mnistwild.py
securemr/__init__.py
securemr/generate_info.py
securemr/pytorch_to_qnn.py
securemr/qnn_model.py
securemr/utils.py
securemr/_bindings/_securemr.cpython-310-x86_64-linux-gnu.so
securemr/_bindings/libSNPE.so
securemr/_bindings/libopencv_calib3d.so.3.4
securemr/_bindings/libopencv_core.so.3.4
securemr/_bindings/libopencv_flann.so.3.4
securemr/_bindings/libopencv_imgcodecs.so.3.4
securemr/_bindings/libopencv_imgproc.so.3.4
securemr/_bindings/libopenmr-backend.so
securemr-0.0.1.dist-info/licenses/LICENSE
tests/__init__.py
tests/test_operator.py
tests/test_pytorch_to_qnn.py
tests/test_tensor.py
tests/test_tensor_mat.py
securemr-0.0.1.dist-info/METADATA
securemr-0.0.1.dist-info/WHEEL
securemr-0.0.1.dist-info/top_level.txt
securemr-0.0.1.dist-info/RECORD
