Metadata-Version: 2.4
Name: securemr
Version: 0.0.1
Summary: Python bindings for SecureMR.
Author-email: "bingwen.ai" <bingwen.ai@bytedance.com>
License: MIT License
Project-URL: repository, https://github.com/Pico-Developer/pySecureMR
Requires-Python: ==3.10.*
License-File: LICENSE
Requires-Dist: numpy<=2.0
Requires-Dist: opencv-python
Requires-Dist: pure-python-adb
Provides-Extra: test
Requires-Dist: coverage; extra == "test"
Requires-Dist: pytest; extra == "test"
Requires-Dist: pytest-xdist; extra == "test"
Requires-Dist: pytest-pythonpath; extra == "test"
Requires-Dist: pytest-cov; extra == "test"
Requires-Dist: pytest-html; extra == "test"
Requires-Dist: pytest-repeat; extra == "test"
Requires-Dist: pytest-watch; extra == "test"
Requires-Dist: mypy==0.910; extra == "test"
Requires-Dist: toml; extra == "test"
Provides-Extra: dev
Requires-Dist: pre-commit>=2.13.0; extra == "dev"
Requires-Dist: pre-commit-hooks>=4.0.1; extra == "dev"
Requires-Dist: isort==5.6.4; extra == "dev"
Requires-Dist: flake8-pyproject; extra == "dev"
Requires-Dist: flake8-bugbear==21.4.3; extra == "dev"
Requires-Dist: flake8-comprehensions==3.6.0; extra == "dev"
Requires-Dist: autoflake==1.4; extra == "dev"
Requires-Dist: black==22.3.0; extra == "dev"
Requires-Dist: pydocstyle==6.1.1; extra == "dev"
Requires-Dist: pep8-naming==0.12.1; extra == "dev"
Requires-Dist: mypy; extra == "dev"
Requires-Dist: build; extra == "dev"
Requires-Dist: twine; extra == "dev"
Dynamic: license-file
